{
    "Name": "Blue Painter",
    "IncludeColorInName": false,
    "Conditions": [
        {
            "Type": "InMainboard",
            "Cards": ["Grindstone"]
        },
        {
            "Type": "InMainboard",
            "Cards": ["Painter's Servant"]
        },
        {
            "Type": "InMainboard",
            "Cards": ["Emry, Lurker of the Loch"]
        },
        {
            "Type": "InMainboard",
            "Cards": ["Seat of the Synod"]
        },
        {
            "Type": "DoesNotContain",
            "Cards": ["Pyroblast"]
        },{
            "Type": "DoesNotContain",
            "Cards": ["Fable of the Mirror-Breaker"]
        }
    ]
}